play_integrity/__init__.py
play_integrity/integrity.py
play_integrity-0.1.2.dist-info/METADATA
play_integrity-0.1.2.dist-info/WHEEL
play_integrity-0.1.2.dist-info/RECORD
